claude/README_LLM.md
claude/__init__.py
claude/core/__init__.py
claude/core/config.py
claude/core/input.py
claude/core/prompt.py
claude/core/utils.py
claude/llm.py
claude/llm_backup/__init__.py
claude/llm_backup/__oai.py
claude/llm_backup/__ollama.py
claude/llm_backup/__util.py
claude/llm_backup/__vllm.py
claude/llm_backup/_qwen.py
claude/llm_backup/add.py
claude/llm_backup/example_usage.py
claude/llm_backup/subtract.py
claude/sample_toolcall.py
claude/test_oai_simple.py
claude/tools/__files_advanced.py
claude/tools/__init__.py
claude/tools/__web.py
claude/tools/_files.py
claude/tools/tool_schemas.py
ceasercode-0.0.33.dist-info/METADATA
ceasercode-0.0.33.dist-info/WHEEL
ceasercode-0.0.33.dist-info/entry_points.txt
ceasercode-0.0.33.dist-info/RECORD
