Metadata-Version: 2.3
Name: ceasercode
Version: 0.0.33
Summary: An AI-powered code agent for workspace operations
License: MIT
Author: Kammari Santhosh
Requires-Python: >=3.11,<4.0
Classifier: License :: OSI Approved :: MIT License
Classifier: Programming Language :: Python :: 3
Classifier: Programming Language :: Python :: 3.11
Classifier: Programming Language :: Python :: 3.12
Classifier: Programming Language :: Python :: 3.13
Project-URL: Repository, https://github.com/santhosh/
